{
  "dur0": 140,
  "dur1": 5,
  "dur2": 79,
  "dur3": 5,
  "dur4": 20,
  "dur5": 32,
  "datetime": "2021-08-25 10:47:15",
  "sort": "1|-1|1|4|1|0|1|-2|0|-1|2|-2|2|3|-2|-4|-1|0|2|-4|3|-3|1|-1|0|-1|-3|-2|2|3|4|-3|0",
  "name": "My_Q_project 1.0",
  "npos": 12,
  "nneu": 7,
  "nneg": 14,
  "userInputId": "---",
  "urlUserCode": "---",
  "accessCode": "---",
  "comment16": "(s16) card 3",
  "comment20": "(s20) card 4",
  "comment31": "(s31) card 1",
  "comment4": "(s4) card 2",
  "form0": "1980",
  "form1": "they were great",
  "form2": "0",
  "form3": "0",
  "form4": "0|1|0",
  "form5": "1|2",
  "form6": "3|3",
  "form7": "9|10"
}
